{
    "nodes": [
        {
            "group": 2,
            "name": "niallceqci",
            "posicao": 1
        },
        {
            "group": 2,
            "name": "AdrianaDriRio",
            "posicao": 2
        },
        {
            "group": 2,
            "name": "MARTINSRJ1",
            "posicao": 3
        },
        {
            "group": 2,
            "name": "STavareis",
            "posicao": 4
        },
        {
            "group": 2,
            "name": "marciagomessil1",
            "posicao": 5
        },
        {
            "group": 2,
            "name": "fontesgilberto",
            "posicao": 6
        },
        {
            "group": 2,
            "name": "rob_scholz",
            "posicao": 7
        },
        {
            "group": 2,
            "name": "apoitia_du",
            "posicao": 8
        },
        {
            "group": 2,
            "name": "a_rj1",
            "posicao": 9
        },
        {
            "group": 2,
            "name": "Canmeira",
            "posicao": 10
        },
        {
            "group": 2,
            "name": "Carmen_Gua",
            "posicao": 11
        },
        {
            "group": 2,
            "name": "RobGreenFields",
            "posicao": 12
        },
        {
            "group": 2,
            "name": "felipebritofb",
            "posicao": 13
        },
        {
            "group": 2,
            "name": "GigioThomaz",
            "posicao": 14
        },
        {
            "group": 2,
            "name": "EltonApollo",
            "posicao": 15
        },
        {
            "group": 2,
            "name": "EtreBr",
            "posicao": 16
        },
        {
            "group": 2,
            "name": "MauricioMLO",
            "posicao": 17
        },
        {
            "group": 2,
            "name": "ALblini",
            "posicao": 18
        },
        {
            "group": 2,
            "name": "danigotesman",
            "posicao": 19
        },
        {
            "group": 2,
            "name": "waltinhoradio",
            "posicao": 20
        },
        {
            "group": 2,
            "name": "Foraptdilma",
            "posicao": 21
        },
        {
            "group": 2,
            "name": "danpontes999",
            "posicao": 22
        },
        {
            "group": 2,
            "name": "caitum",
            "posicao": 23
        },
        {
            "group": 2,
            "name": "ronaldoliveira2",
            "posicao": 24
        },
        {
            "group": 2,
            "name": "GIFFONIBRAVO",
            "posicao": 25
        },
        {
            "group": 2,
            "name": "davidfcesar",
            "posicao": 26
        },
        {
            "group": 2,
            "name": "LeonardoFM11",
            "posicao": 27
        },
        {
            "group": 2,
            "name": "matheusft82",
            "posicao": 28
        },
        {
            "group": 2,
            "name": "alves_truz",
            "posicao": 29
        },
        {
            "group": 2,
            "name": "ef96d509580b484",
            "posicao": 30
        },
        {
            "group": 2,
            "name": "abadeduda",
            "posicao": 31
        },
        {
            "group": 2,
            "name": "Reginar_r",
            "posicao": 32
        },
        {
            "group": 2,
            "name": "GuaracidaCruz",
            "posicao": 33
        },
        {
            "group": 2,
            "name": "talitatrainer",
            "posicao": 34
        },
        {
            "group": 2,
            "name": "hudsondesouza11",
            "posicao": 35
        },
        {
            "group": 2,
            "name": "gigioedudu",
            "posicao": 36
        },
        {
            "group": 2,
            "name": "tiagocamassutti",
            "posicao": 37
        },
        {
            "group": 2,
            "name": "alvim93",
            "posicao": 38
        },
        {
            "group": 2,
            "name": "Nelson_Harter",
            "posicao": 39
        },
        {
            "group": 2,
            "name": "MARGARETHALBUQU",
            "posicao": 40
        },
        {
            "group": 2,
            "name": "goxtosaxim",
            "posicao": 41
        },
        {
            "group": 2,
            "name": "DefesaHetero",
            "posicao": 42
        },
        {
            "group": 2,
            "name": "BordinVania",
            "posicao": 43
        },
        {
            "group": 2,
            "name": "luciaturchetto",
            "posicao": 44
        },
        {
            "group": 2,
            "name": "Cellofla45",
            "posicao": 45
        },
        {
            "group": 2,
            "name": "JokerBH666",
            "posicao": 46
        },
        {
            "group": 2,
            "name": "caboff1",
            "posicao": 47
        },
        {
            "group": 2,
            "name": "rafaeldmatheus",
            "posicao": 48
        },
        {
            "group": 2,
            "name": "adijsantos",
            "posicao": 49
        },
        {
            "group": 2,
            "name": "Hwidger",
            "posicao": 50
        },
        {
            "group": 2,
            "name": "anaalmeidaca38",
            "posicao": 51
        },
        {
            "group": 2,
            "name": "ninarosacorrea",
            "posicao": 52
        },
        {
            "group": 2,
            "name": "AcordouAcordou",
            "posicao": 53
        },
        {
            "group": 2,
            "name": "RenatoKedson",
            "posicao": 54
        },
        {
            "group": 2,
            "name": "MancheteReal",
            "posicao": 55
        },
        {
            "group": 2,
            "name": "marchezan_",
            "posicao": 56
        },
        {
            "group": 2,
            "name": "euudisseque",
            "posicao": 57
        },
        {
            "group": 2,
            "name": "lobaoeletrico",
            "posicao": 58
        },
        {
            "group": 2,
            "name": "earcarmona",
            "posicao": 59
        },
        {
            "group": 2,
            "name": "rakelmaia55",
            "posicao": 60
        },
        {
            "group": 2,
            "name": "ThomasAlencar11",
            "posicao": 61
        },
        {
            "group": 2,
            "name": "rebecajulia17",
            "posicao": 62
        },
        {
            "group": 2,
            "name": "sountilurmine",
            "posicao": 63
        },
        {
            "group": 2,
            "name": "demattosmonica",
            "posicao": 64
        },
        {
            "group": 2,
            "name": "seibel10",
            "posicao": 65
        },
        {
            "group": 2,
            "name": "Bruno_Lams",
            "posicao": 66
        },
        {
            "group": 2,
            "name": "belfonseca19",
            "posicao": 67
        },
        {
            "group": 2,
            "name": "LeoCastroMat",
            "posicao": 68
        },
        {
            "group": 2,
            "name": "MarchemosBrasil",
            "posicao": 69
        },
        {
            "group": 2,
            "name": "MegVinhas",
            "posicao": 70
        },
        {
            "group": 2,
            "name": "claudemir19791",
            "posicao": 71
        },
        {
            "group": 2,
            "name": "Arcamargo70",
            "posicao": 72
        },
        {
            "group": 2,
            "name": "milconcei",
            "posicao": 73
        },
        {
            "group": 2,
            "name": "New_Delia",
            "posicao": 74
        },
        {
            "group": 2,
            "name": "motter_ja",
            "posicao": 75
        },
        {
            "group": 2,
            "name": "parabensatodos",
            "posicao": 76
        },
        {
            "group": 2,
            "name": "1Notadade",
            "posicao": 77
        },
        {
            "group": 2,
            "name": "robertaelke",
            "posicao": 78
        },
        {
            "group": 2,
            "name": "DenniscafeZz",
            "posicao": 79
        },
        {
            "group": 2,
            "name": "rbuobu",
            "posicao": 80
        },
        {
            "group": 2,
            "name": "CleuzaBapti",
            "posicao": 81
        },
        {
            "group": 2,
            "name": "emerson_carlos",
            "posicao": 82
        },
        {
            "group": 2,
            "name": "MarcoCampelo",
            "posicao": 83
        },
        {
            "group": 2,
            "name": "cpidopt",
            "posicao": 84
        },
        {
            "group": 2,
            "name": "alanferrazrj",
            "posicao": 85
        },
        {
            "group": 2,
            "name": "ChrisTheBoy_",
            "posicao": 86
        },
        {
            "group": 2,
            "name": "Mimy_2014",
            "posicao": 87
        },
        {
            "group": 2,
            "name": "mariagcas",
            "posicao": 88
        },
        {
            "group": 2,
            "name": "FBI_NOTICIAS",
            "posicao": 89
        },
        {
            "group": 2,
            "name": "joeoficial2014",
            "posicao": 90
        },
        {
            "group": 2,
            "name": "MarcusVini_17",
            "posicao": 91
        },
        {
            "group": 2,
            "name": "Anadi_Paula",
            "posicao": 92
        },
        {
            "group": 2,
            "name": "horandivando",
            "posicao": 93
        },
        {
            "group": 2,
            "name": "marilumgon",
            "posicao": 94
        },
        {
            "group": 2,
            "name": "marcelospfcbt",
            "posicao": 95
        },
        {
            "group": 2,
            "name": "jacksonsimoes",
            "posicao": 96
        },
        {
            "group": 2,
            "name": "TopTV_Brasil",
            "posicao": 97
        },
        {
            "group": 2,
            "name": "washing38204826",
            "posicao": 98
        },
        {
            "group": 2,
            "name": "Marlene_Senna",
            "posicao": 99
        },
        {
            "group": 2,
            "name": "AndreaFigueired",
            "posicao": 100
        },
        {
            "group": 2,
            "name": "PaulGilmar",
            "posicao": 101
        },
        {
            "group": 2,
            "name": "br12ro",
            "posicao": 102
        },
        {
            "group": 2,
            "name": "otaviopaz",
            "posicao": 103
        },
        {
            "group": 2,
            "name": "marcelincoelho",
            "posicao": 104
        },
        {
            "group": 2,
            "name": "Marcosguaiba",
            "posicao": 105
        },
        {
            "group": 2,
            "name": "koramulata",
            "posicao": 106
        },
        {
            "group": 2,
            "name": "Foxnews1",
            "posicao": 107
        },
        {
            "group": 2,
            "name": "fataloliveira1",
            "posicao": 108
        },
        {
            "group": 2,
            "name": "geacarlobc",
            "posicao": 109
        },
        {
            "group": 2,
            "name": "JongaPereira",
            "posicao": 110
        },
        {
            "group": 2,
            "name": "fabioq",
            "posicao": 111
        },
        {
            "group": 2,
            "name": "nelsonspartacus",
            "posicao": 112
        },
        {
            "group": 2,
            "name": "BcAlemao",
            "posicao": 113
        },
        {
            "group": 2,
            "name": "_NaoVaiTerCopa",
            "posicao": 114
        },
        {
            "group": 2,
            "name": "marcelomformiga",
            "posicao": 115
        },
        {
            "group": 2,
            "name": "fabiocs",
            "posicao": 116
        },
        {
            "group": 2,
            "name": "mildignos",
            "posicao": 117
        },
        {
            "group": 2,
            "name": "DuuLima23",
            "posicao": 118
        },
        {
            "group": 2,
            "name": "marcia_umari",
            "posicao": 119
        },
        {
            "group": 2,
            "name": "dalvinha47",
            "posicao": 120
        },
        {
            "group": 2,
            "name": "SeiSei0",
            "posicao": 121
        },
        {
            "group": 2,
            "name": "letrin45",
            "posicao": 122
        },
        {
            "group": 2,
            "name": "Tom_brz",
            "posicao": 123
        },
        {
            "group": 2,
            "name": "Dehavasan",
            "posicao": 124
        },
        {
            "group": 2,
            "name": "sandrassabino",
            "posicao": 125
        },
        {
            "group": 2,
            "name": "AndreDecoy",
            "posicao": 126
        },
        {
            "group": 2,
            "name": "themaloya",
            "posicao": 127
        },
        {
            "group": 2,
            "name": "livbuk22",
            "posicao": 128
        },
        {
            "group": 2,
            "name": "DrRobertoSalles",
            "posicao": 129
        },
        {
            "group": 2,
            "name": "mariovgomes",
            "posicao": 130
        },
        {
            "group": 2,
            "name": "Silvio_MKT",
            "posicao": 131
        },
        {
            "group": 2,
            "name": "lula_oliveira",
            "posicao": 132
        },
        {
            "group": 2,
            "name": "dellFerraz",
            "posicao": 133
        },
        {
            "group": 2,
            "name": "JulianoSMendes",
            "posicao": 134
        },
        {
            "group": 2,
            "name": "Rituska_",
            "posicao": 135
        },
        {
            "group": 2,
            "name": "zaninella",
            "posicao": 136
        },
        {
            "group": 2,
            "name": "AdrianoLourenco",
            "posicao": 137
        },
        {
            "group": 2,
            "name": "FabiAgenteCIA",
            "posicao": 138
        },
        {
            "group": 2,
            "name": "danmunakata",
            "posicao": 139
        },
        {
            "group": 2,
            "name": "gdugomes",
            "posicao": 140
        },
        {
            "group": 2,
            "name": "JDarzone",
            "posicao": 141
        },
        {
            "group": 2,
            "name": "Geraldo_Olivera",
            "posicao": 142
        },
        {
            "group": 2,
            "name": "AyurvedaPoa",
            "posicao": 143
        },
        {
            "group": 2,
            "name": "Rabbits_ca",
            "posicao": 144
        },
        {
            "group": 2,
            "name": "pinheirolettici",
            "posicao": 145
        },
        {
            "group": 2,
            "name": "PORTO_Nat",
            "posicao": 146
        },
        {
            "group": 2,
            "name": "PanchRapha",
            "posicao": 147
        },
        {
            "group": 2,
            "name": "Wanderson_Panch",
            "posicao": 148
        },
        {
            "group": 2,
            "name": "letrasLTDA",
            "posicao": 149
        },
        {
            "group": 2,
            "name": "Gabrielgalura",
            "posicao": 150
        },
        {
            "group": 2,
            "name": "Chiwizz1",
            "posicao": 151
        },
        {
            "group": 2,
            "name": "aparecidapz",
            "posicao": 152
        },
        {
            "group": 2,
            "name": "obrasil_e_nosso",
            "posicao": 153
        },
        {
            "group": 2,
            "name": "OsvladPereira",
            "posicao": 154
        },
        {
            "group": 2,
            "name": "TO_DE_OLHO",
            "posicao": 155
        },
        {
            "group": 2,
            "name": "guidomelo1",
            "posicao": 156
        },
        {
            "group": 2,
            "name": "RumoCertoSim",
            "posicao": 157
        },
        {
            "group": 2,
            "name": "_Lavoisier",
            "posicao": 158
        },
        {
            "group": 2,
            "name": "writeslaureen",
            "posicao": 159
        },
        {
            "group": 2,
            "name": "lourdesmsantos",
            "posicao": 160
        },
        {
            "group": 2,
            "name": "PaulXbrow2",
            "posicao": 161
        },
        {
            "group": 2,
            "name": "tpequeno",
            "posicao": 162
        },
        {
            "group": 2,
            "name": "nizetticardoso",
            "posicao": 163
        },
        {
            "group": 2,
            "name": "h_jordon",
            "posicao": 164
        },
        {
            "group": 2,
            "name": "LauraVieiraDias",
            "posicao": 165
        },
        {
            "group": 2,
            "name": "WallaceLarri",
            "posicao": 166
        },
        {
            "group": 2,
            "name": "JoceyrR",
            "posicao": 167
        },
        {
            "group": 2,
            "name": "fabistrada",
            "posicao": 168
        },
        {
            "group": 2,
            "name": "Brasangola_",
            "posicao": 169
        },
        {
            "group": 2,
            "name": "ZeferinoJanio",
            "posicao": 170
        },
        {
            "group": 2,
            "name": "voliasobral2",
            "posicao": 171
        },
        {
            "group": 2,
            "name": "fcarravetta",
            "posicao": 172
        },
        {
            "group": 2,
            "name": "MaxBrasil2000",
            "posicao": 173
        },
        {
            "group": 2,
            "name": "euzenidwelder",
            "posicao": 174
        },
        {
            "group": 2,
            "name": "JoeClementino",
            "posicao": 175
        },
        {
            "group": 2,
            "name": "Odara_10",
            "posicao": 176
        },
        {
            "group": 2,
            "name": "CleytondeMelo",
            "posicao": 177
        },
        {
            "group": 2,
            "name": "gatosarado2016",
            "posicao": 178
        },
        {
            "group": 2,
            "name": "pedroceleste",
            "posicao": 179
        },
        {
            "group": 2,
            "name": "carmemsouza",
            "posicao": 180
        },
        {
            "group": 2,
            "name": "luis13vieira",
            "posicao": 181
        },
        {
            "group": 2,
            "name": "mgfufino",
            "posicao": 182
        },
        {
            "group": 2,
            "name": "511921hgq",
            "posicao": 183
        },
        {
            "group": 2,
            "name": "RafaelAtari",
            "posicao": 184
        },
        {
            "group": 2,
            "name": "bonnieximena",
            "posicao": 185
        },
        {
            "group": 2,
            "name": "REGINAOUTEIRO",
            "posicao": 186
        },
        {
            "group": 2,
            "name": "frostlost",
            "posicao": 187
        },
        {
            "group": 2,
            "name": "pauloquaresma2",
            "posicao": 188
        },
        {
            "group": 2,
            "name": "jadsonlima2010",
            "posicao": 189
        },
        {
            "group": 2,
            "name": "patggou1",
            "posicao": 190
        },
        {
            "group": 2,
            "name": "arcofi",
            "posicao": 191
        },
        {
            "group": 2,
            "name": "iojandaira",
            "posicao": 192
        },
        {
            "group": 2,
            "name": "ffmadruga",
            "posicao": 193
        },
        {
            "group": 2,
            "name": "SacraSandra",
            "posicao": 194
        },
        {
            "group": 2,
            "name": "RojanioMarcio",
            "posicao": 195
        },
        {
            "group": 2,
            "name": "adriano_francaa",
            "posicao": 196
        },
        {
            "group": 2,
            "name": "wellingtonmoura",
            "posicao": 197
        },
        {
            "group": 2,
            "name": "agadanymanu",
            "posicao": 198
        },
        {
            "group": 2,
            "name": "MariRemor",
            "posicao": 199
        },
        {
            "group": 2,
            "name": "maria_padu",
            "posicao": 200
        },
        {
            "group": 2,
            "name": "AnaPaulaVendri",
            "posicao": 201
        },
        {
            "group": 2,
            "name": "OpusckiSulains",
            "posicao": 202
        },
        {
            "group": 2,
            "name": "vishtati",
            "posicao": 203
        },
        {
            "group": 2,
            "name": "maraferro228",
            "posicao": 204
        },
        {
            "group": 2,
            "name": "wondergio",
            "posicao": 205
        },
        {
            "group": 2,
            "name": "cacildanc",
            "posicao": 206
        },
        {
            "group": 2,
            "name": "aeciofaraujo",
            "posicao": 207
        },
        {
            "group": 2,
            "name": "prmaduro",
            "posicao": 208
        },
        {
            "group": 2,
            "name": "sergio_pm",
            "posicao": 209
        },
        {
            "group": 2,
            "name": "fernanda281327",
            "posicao": 210
        },
        {
            "group": 2,
            "name": "BlogDoTato67",
            "posicao": 211
        },
        {
            "group": 2,
            "name": "OdilonTesser",
            "posicao": 212
        },
        {
            "group": 2,
            "name": "ptnuncamais",
            "posicao": 213
        },
        {
            "group": 2,
            "name": "neocomunicabh",
            "posicao": 214
        },
        {
            "group": 2,
            "name": "naskarmit",
            "posicao": 215
        },
        {
            "group": 2,
            "name": "Renato_SVP",
            "posicao": 216
        },
        {
            "group": 2,
            "name": "Dorasil76578668",
            "posicao": 217
        },
        {
            "group": 2,
            "name": "Braph_torres",
            "posicao": 218
        },
        {
            "group": 2,
            "name": "XeniaAntunes",
            "posicao": 219
        },
        {
            "group": 2,
            "name": "luciamoura00",
            "posicao": 220
        },
        {
            "group": 2,
            "name": "AbdoFortunato",
            "posicao": 221
        },
        {
            "group": 2,
            "name": "katiaduarte",
            "posicao": 222
        },
        {
            "group": 2,
            "name": "OgroRevoltado",
            "posicao": 223
        },
        {
            "group": 2,
            "name": "fitzca",
            "posicao": 224
        }
    ],
    "links": [
        {
            "source": 1,
            "target": 16,
            "value": 1
        },
        {
            "source": 2,
            "target": 16,
            "value": 1
        },
        {
            "source": 3,
            "target": 16,
            "value": 1
        },
        {
            "source": 7,
            "target": 16,
            "value": 1
        },
        {
            "source": 8,
            "target": 56,
            "value": 1
        },
        {
            "source": 9,
            "target": 16,
            "value": 1
        },
        {
            "source": 10,
            "target": 16,
            "value": 1
        },
        {
            "source": 11,
            "target": 56,
            "value": 1
        },
        {
            "source": 13,
            "target": 16,
            "value": 1
        },
        {
            "source": 14,
            "target": 56,
            "value": 1
        },
        {
            "source": 15,
            "target": 56,
            "value": 1
        },
        {
            "source": 15,
            "target": 16,
            "value": 1
        },
        {
            "source": 18,
            "target": 56,
            "value": 1
        },
        {
            "source": 19,
            "target": 56,
            "value": 1
        },
        {
            "source": 20,
            "target": 56,
            "value": 1
        },
        {
            "source": 21,
            "target": 56,
            "value": 1
        },
        {
            "source": 22,
            "target": 16,
            "value": 1
        },
        {
            "source": 23,
            "target": 16,
            "value": 1
        },
        {
            "source": 24,
            "target": 56,
            "value": 1
        },
        {
            "source": 25,
            "target": 56,
            "value": 1
        },
        {
            "source": 27,
            "target": 16,
            "value": 1
        },
        {
            "source": 28,
            "target": 56,
            "value": 1
        },
        {
            "source": 29,
            "target": 16,
            "value": 1
        },
        {
            "source": 30,
            "target": 56,
            "value": 1
        },
        {
            "source": 31,
            "target": 56,
            "value": 1
        },
        {
            "source": 32,
            "target": 56,
            "value": 1
        },
        {
            "source": 33,
            "target": 56,
            "value": 1
        },
        {
            "source": 34,
            "target": 56,
            "value": 1
        },
        {
            "source": 35,
            "target": 56,
            "value": 1
        },
        {
            "source": 36,
            "target": 56,
            "value": 1
        },
        {
            "source": 37,
            "target": 56,
            "value": 1
        },
        {
            "source": 38,
            "target": 56,
            "value": 1
        },
        {
            "source": 39,
            "target": 56,
            "value": 1
        },
        {
            "source": 40,
            "target": 56,
            "value": 1
        },
        {
            "source": 41,
            "target": 56,
            "value": 1
        },
        {
            "source": 43,
            "target": 56,
            "value": 1
        },
        {
            "source": 44,
            "target": 16,
            "value": 1
        },
        {
            "source": 45,
            "target": 56,
            "value": 1
        },
        {
            "source": 46,
            "target": 56,
            "value": 1
        },
        {
            "source": 47,
            "target": 16,
            "value": 1
        },
        {
            "source": 48,
            "target": 56,
            "value": 1
        },
        {
            "source": 49,
            "target": 56,
            "value": 1
        },
        {
            "source": 50,
            "target": 16,
            "value": 1
        },
        {
            "source": 52,
            "target": 56,
            "value": 1
        },
        {
            "source": 17,
            "target": 16,
            "value": 1
        },
        {
            "source": 54,
            "target": 56,
            "value": 1
        },
        {
            "source": 55,
            "target": 56,
            "value": 1
        },
        {
            "source": 17,
            "target": 56,
            "value": 1
        },
        {
            "source": 58,
            "target": 56,
            "value": 1
        },
        {
            "source": 59,
            "target": 56,
            "value": 1
        },
        {
            "source": 53,
            "target": 16,
            "value": 1
        },
        {
            "source": 53,
            "target": 56,
            "value": 1
        },
        {
            "source": 60,
            "target": 16,
            "value": 1
        },
        {
            "source": 65,
            "target": 56,
            "value": 1
        },
        {
            "source": 68,
            "target": 56,
            "value": 1
        },
        {
            "source": 71,
            "target": 78,
            "value": 1
        },
        {
            "source": 72,
            "target": 56,
            "value": 1
        },
        {
            "source": 75,
            "target": 78,
            "value": 1
        },
        {
            "source": 76,
            "target": 78,
            "value": 1
        },
        {
            "source": 77,
            "target": 56,
            "value": 1
        },
        {
            "source": 2,
            "target": 78,
            "value": 1
        },
        {
            "source": 79,
            "target": 78,
            "value": 1
        },
        {
            "source": 80,
            "target": 56,
            "value": 1
        },
        {
            "source": 81,
            "target": 56,
            "value": 1
        },
        {
            "source": 83,
            "target": 56,
            "value": 1
        },
        {
            "source": 84,
            "target": 56,
            "value": 1
        },
        {
            "source": 86,
            "target": 78,
            "value": 1
        },
        {
            "source": 87,
            "target": 78,
            "value": 1
        },
        {
            "source": 88,
            "target": 56,
            "value": 1
        },
        {
            "source": 89,
            "target": 78,
            "value": 1
        },
        {
            "source": 90,
            "target": 78,
            "value": 1
        },
        {
            "source": 91,
            "target": 78,
            "value": 1
        },
        {
            "source": 92,
            "target": 78,
            "value": 1
        },
        {
            "source": 94,
            "target": 56,
            "value": 1
        },
        {
            "source": 95,
            "target": 78,
            "value": 1
        },
        {
            "source": 96,
            "target": 56,
            "value": 1
        },
        {
            "source": 97,
            "target": 78,
            "value": 1
        },
        {
            "source": 85,
            "target": 78,
            "value": 1
        },
        {
            "source": 100,
            "target": 56,
            "value": 1
        },
        {
            "source": 101,
            "target": 56,
            "value": 1
        },
        {
            "source": 102,
            "target": 56,
            "value": 1
        },
        {
            "source": 103,
            "target": 56,
            "value": 1
        },
        {
            "source": 105,
            "target": 56,
            "value": 1
        },
        {
            "source": 106,
            "target": 158,
            "value": 1
        },
        {
            "source": 107,
            "target": 56,
            "value": 1
        },
        {
            "source": 108,
            "target": 56,
            "value": 1
        },
        {
            "source": 112,
            "target": 56,
            "value": 1
        },
        {
            "source": 113,
            "target": 56,
            "value": 1
        },
        {
            "source": 114,
            "target": 56,
            "value": 1
        },
        {
            "source": 115,
            "target": 56,
            "value": 1
        },
        {
            "source": 116,
            "target": 56,
            "value": 1
        },
        {
            "source": 117,
            "target": 56,
            "value": 1
        },
        {
            "source": 118,
            "target": 56,
            "value": 1
        },
        {
            "source": 119,
            "target": 56,
            "value": 1
        },
        {
            "source": 120,
            "target": 56,
            "value": 1
        },
        {
            "source": 121,
            "target": 56,
            "value": 1
        },
        {
            "source": 122,
            "target": 56,
            "value": 1
        },
        {
            "source": 123,
            "target": 56,
            "value": 1
        },
        {
            "source": 124,
            "target": 56,
            "value": 1
        },
        {
            "source": 125,
            "target": 56,
            "value": 1
        },
        {
            "source": 127,
            "target": 56,
            "value": 1
        },
        {
            "source": 129,
            "target": 56,
            "value": 1
        },
        {
            "source": 130,
            "target": 56,
            "value": 1
        },
        {
            "source": 131,
            "target": 56,
            "value": 1
        },
        {
            "source": 133,
            "target": 56,
            "value": 1
        },
        {
            "source": 134,
            "target": 56,
            "value": 1
        },
        {
            "source": 136,
            "target": 56,
            "value": 1
        },
        {
            "source": 137,
            "target": 56,
            "value": 1
        },
        {
            "source": 138,
            "target": 56,
            "value": 1
        },
        {
            "source": 139,
            "target": 56,
            "value": 1
        },
        {
            "source": 140,
            "target": 56,
            "value": 1
        },
        {
            "source": 141,
            "target": 56,
            "value": 1
        },
        {
            "source": 142,
            "target": 56,
            "value": 1
        },
        {
            "source": 143,
            "target": 56,
            "value": 1
        },
        {
            "source": 145,
            "target": 56,
            "value": 1
        },
        {
            "source": 147,
            "target": 148,
            "value": 1
        },
        {
            "source": 147,
            "target": 148,
            "value": 1
        },
        {
            "source": 147,
            "target": 148,
            "value": 1
        },
        {
            "source": 149,
            "target": 56,
            "value": 1
        },
        {
            "source": 150,
            "target": 56,
            "value": 1
        },
        {
            "source": 151,
            "target": 56,
            "value": 1
        },
        {
            "source": 152,
            "target": 56,
            "value": 1
        },
        {
            "source": 153,
            "target": 213,
            "value": 1
        },
        {
            "source": 154,
            "target": 56,
            "value": 1
        },
        {
            "source": 155,
            "target": 56,
            "value": 1
        },
        {
            "source": 157,
            "target": 158,
            "value": 1
        },
        {
            "source": 168,
            "target": 206,
            "value": 1
        },
        {
            "source": 170,
            "target": 56,
            "value": 1
        },
        {
            "source": 172,
            "target": 56,
            "value": 1
        },
        {
            "source": 173,
            "target": 190,
            "value": 1
        },
        {
            "source": 175,
            "target": 190,
            "value": 1
        },
        {
            "source": 182,
            "target": 190,
            "value": 1
        },
        {
            "source": 184,
            "target": 190,
            "value": 1
        },
        {
            "source": 185,
            "target": 191,
            "value": 1
        },
        {
            "source": 186,
            "target": 190,
            "value": 1
        },
        {
            "source": 187,
            "target": 190,
            "value": 1
        },
        {
            "source": 188,
            "target": 191,
            "value": 1
        },
        {
            "source": 189,
            "target": 190,
            "value": 1
        },
        {
            "source": 150,
            "target": 190,
            "value": 1
        },
        {
            "source": 170,
            "target": 191,
            "value": 1
        },
        {
            "source": 74,
            "target": 191,
            "value": 1
        },
        {
            "source": 192,
            "target": 208,
            "value": 1
        },
        {
            "source": 194,
            "target": 213,
            "value": 1
        },
        {
            "source": 197,
            "target": 213,
            "value": 1
        },
        {
            "source": 199,
            "target": 191,
            "value": 1
        },
        {
            "source": 200,
            "target": 213,
            "value": 1
        },
        {
            "source": 202,
            "target": 206,
            "value": 1
        },
        {
            "source": 168,
            "target": 206,
            "value": 1
        },
        {
            "source": 207,
            "target": 211,
            "value": 1
        },
        {
            "source": 94,
            "target": 208,
            "value": 1
        },
        {
            "source": 210,
            "target": 211,
            "value": 1
        },
        {
            "source": 210,
            "target": 211,
            "value": 1
        },
        {
            "source": 212,
            "target": 213,
            "value": 1
        },
        {
            "source": 41,
            "target": 213,
            "value": 1
        },
        {
            "source": 41,
            "target": 214,
            "value": 1
        },
        {
            "source": 210,
            "target": 213,
            "value": 1
        },
        {
            "source": 215,
            "target": 213,
            "value": 1
        },
        {
            "source": 216,
            "target": 213,
            "value": 1
        },
        {
            "source": 217,
            "target": 213,
            "value": 1
        },
        {
            "source": 219,
            "target": 213,
            "value": 1
        },
        {
            "source": 220,
            "target": 208,
            "value": 1
        },
        {
            "source": 221,
            "target": 213,
            "value": 1
        },
        {
            "source": 222,
            "target": 213,
            "value": 1
        },
        {
            "source": 129,
            "target": 213,
            "value": 1
        },
        {
            "source": 210,
            "target": 214,
            "value": 1
        },
        {
            "source": 213,
            "target": 214,
            "value": 1
        }
    ]
}
